feishu/__init__.py
feishu/baseclient.py
feishu/client.py
feishu/consts.py
feishu/errors.py
feishu/server.py
feishu/stores.py
feishu/version.py
feishu/apis/__init__.py
feishu/apis/api.py
feishu/apis/auth.py
feishu/apis/base.py
feishu/apis/bot.py
feishu/apis/card.py
feishu/apis/event.py
feishu/apis/message.py
feishu/models/__init__.py
feishu/models/bots.py
feishu/models/events/__init__.py
feishu/models/events/app.py
feishu/models/events/approval.py
feishu/models/events/base.py
feishu/models/events/bot.py
feishu/models/events/calendar.py
feishu/models/events/card.py
feishu/models/events/chat.py
feishu/models/events/contact.py
feishu/models/messages/__init__.py
feishu/models/messages/card.py
feishu/models/messages/message.py
tests/__init__.py
tests/servertest.py
tests/sometest.py
tests/test_allow_async_call.py
tests/test_api_auth.py
tests/test_decrypt_aes.py
feishu_python_sdk-0.1.2.dist-info/METADATA
feishu_python_sdk-0.1.2.dist-info/WHEEL
feishu_python_sdk-0.1.2.dist-info/top_level.txt
feishu_python_sdk-0.1.2.dist-info/RECORD
