Metadata-Version: 2.1
Name: feishu-python-sdk
Version: 0.1.2
Summary: 一个用于和飞书开放平台交互的python库
Home-page: https://github.com/cyclone-robotics/feishu
Author: Cyclone Chatbot Dev
Author-email: jingchao.hu@cyclone-robotics.com
License: UNKNOWN
Platform: UNKNOWN
Classifier: Programming Language :: Python :: 3
Classifier: License :: OSI Approved :: MIT License
Classifier: Operating System :: OS Independent
Requires-Python: >=3.7
Requires-Dist: pydantic (~=1.6.1)
Requires-Dist: Flask (~=1.1.2)
Requires-Dist: aiohttp (~=3.6.2)
Requires-Dist: requests (~=2.24.0)
Requires-Dist: cryptography (~=3.1)
